Workbook

Sheet Формула
A1: Модель целевой структуры направления «Брокерское обслуживание» после внедрения ИИ-агентов
A3: Жёлтые ячейки — входные параметры. Остальное считается формулами.
A5: 1. Экономия вида работ i (доля часов, которую снимает ИИ):
A6: E_i = Σ_j w_ij × a_ij
A7: w_ij — доля атома j в трудозатратах вида работ i (в часах, не в сроке); a_ij — насколько ИИ сокращает часы атома.
A9: 2. Потребность в исполнителях (аналитики, разработчики, тестировщики-DevOps):
A10: FTE_TO-BE = (Σ_i FTE_i × (1 − k × E_i)) × (1 + o) − R
A11: k — доля потока задач, которая реально идёт через агентов на конец года;
A12: o — новые накладные расходы: ревью результатов агентов и доводка пайплайна;
A13: R — меньше переделок благодаря Intent-команде: R = FTE изменений после ИИ × доля переделок × снижение переделок.
A15: 3. Численность:
A16: Всего = исполнители в командах + Intent-команда + руководители команд + роли вне команд
... A25: Листы: «Параметры» — вводные; «Атомы» — разложение работ и коэффициенты ИИ по ролям; «Расчёт» — экономия и потребность по сценариям; «Структура» — целевые команды и сверка с потребностью.

Sheet Параметры
A1: Параметры модели
A3: Штат AS-IS | B3: Значение
A4: Команд | B4: 6
A5: Руководителей в команде | B5: 1
A6: Аналитиков в команде | B6: 2
A7: Разработчиков в команде | B7: 4
A8: Тестировщиков-DevOps в команде | B8: 2
A9: Ролей вне команд (не ускоряются ИИ) | B9: 6
A10: Исполнителей AS-IS (аналитики + разработчики + тестировщики-DevOps) | B10: =B4*(B6+B7+B8) -> 48
A11: Всего AS-IS | B11: =B4*(B5+B6+B7+B8)+B9 -> 60
A13: Вид работ | B13: Доля трудозатрат | C13: FTE исполнителей | D13: Группа атомов
A14: Заказные доработки | B14: 0.2 | C14: =B14*$B$10 -> 9.6 | D14: Изменения
A15: Поддержка законодательства | B15: 0.3 | C15: =B15*$B$10 -> 14.4 | D15: Изменения
A16: Развитие продукта | B16: 0.1 | C16: =B16*$B$10 -> 4.8 | D16: Изменения
A17: Поддержка проектов внедрения | B17: 0.1 | C17: =B17*$B$10 -> 4.8 | D17: Внедрение
A18: Сопровождение | B18: 0.25 | C18: =B18*$B$10 -> 12 | D18: Сопровождение
A19: Пресейлы и обследования | B19: 0.05 | C19: =B19*$B$10 -> 2.4 | D19: Пресейлы
A20: Итого | B20: =SUM(B14:B19) -> 1 | C20: =SUM(C14:C19) -> 48
A22: Параметры сценариев | B22: Консервативный | C22: Базовый | D22: Оптимистичный
A23: k — доля потока через агентов на конец года | B23: 0.8 | C23: 1 | D23: 1
A24: Набор коэффициентов ИИ (база / опт) | B24: база | C24: база | D24: опт
A25: o — накладные ИИ (ревью агентов, доводка пайплайна) | B25: 0.05 | C25: 0.05 | D25: 0.05
A26: Доля переделок в трудозатратах изменений | B26: 0.15 | C26: 0.15 | D26: 0.15
A27: Снижение переделок за счёт Intent-команды | B27: 0.33333333 | C27: 0.33333333 | D27: 0.33333333
A29: Прочие параметры | B29: Значение
A30: Доля входной аналитики изменений через Intent-команду | B30: 0.7
A31: Доля времени руководителя команды на задачах | B31: 0.5
A32: Накладные ИИ: доля разработчиков | B32: 0.5
A33: Накладные ИИ: доля тестировщиков-DevOps | B33: 0.5
A34: Снижение переделок: доля аналитиков | B34: 0.3
A35: Снижение переделок: доля разработчиков | B35: 0.3
A36: Снижение переделок: доля тестировщиков-DevOps | B36: 0.4

Sheet Атомы
A1: Разложение работ на атомы: доля в часах, экономия за счёт ИИ, кто выполняет
A2: Доли w внутри каждой группы в сумме дают 100%. Роли: А — аналитик, Р — разработчик, Т — тестировщик-DevOps.
A4: Группа | B4: Блок | C4: Атом работы | D4: Что делает ИИ | E4: w, доля часов | F4: a база | G4: a опт | H4: Доля А | I4: Доля Р | J4: Доля Т | K4: Доля Intent | L4: Остаток база | M4: Остаток опт
A5: Изменения | B5: Аналитика | C5: Встречи, интервью, согласования с заказчиком | D5: Протоколы, резюме, список открытых вопросов; сами переговоры не ускоряет | E5: 0.12 | F5: 0.1 | G5: 0.1 | H5: 1 | I5: 0 | J5: 0 | K5: =Параметры!$B$30 -> 0.7 | L5: =E5*(1-F5) -> 0.108 | M5: =E5*(1-G5) -> 0.108
A6: Изменения | B6: Аналитика | C6: Разбор нормативки, ТЗ и текущей логики продукта | D6: Поиск и сравнение норм, выжимка изменений, поиск затронутого кода и настроек | E6: 0.08 | F6: 0.4 | G6: 0.5 | H6: 1 | I6: 0 | J6: 0 | K6: =Параметры!$B$30 -> 0.7 | L6: =E6*(1-F6) -> 0.048 | M6: =E6*(1-G6) -> 0.04
A7: Изменения | B7: Аналитика | C7: Постановка и спецификация (Proposal.md) | D7: Черновик постановки, сценарии и критерии приёмки по шаблону | E7: 0.1 | F7: 0.5 | G7: 0.6 | H7: 1 | I7: 0 | J7: 0 | K7: 0 | L7: =E7*(1-F7) -> 0.05 | M7: =E7*(1-G7) -> 0.04
A8: Изменения | B8: Разработка | C8: Проектирование решения | D8: Варианты решения и анализ влияния; решение принимает человек | E8: 0.05 | F8: 0.2 | G8: 0.3 | H8: 0 | I8: 1 | J8: 0 | K8: 0 | L8: =E8*(1-F8) -> 0.04 | M8: =E8*(1-G8) -> 0.035
A9: Изменения | B9: Разработка | C9: Написание кода | D9: Агент пишет код по постановке | E9: 0.15 | F9: 0.5 | G9: 0.6 | H9: 0 | I9: 1 | J9: 0 | K9: 0 | L9: =E9*(1-F9) -> 0.075 | M9: =E9*(1-G9) -> 0.06
A10: Изменения | B10: Разработка | C10: Ревью, отладка, merge | D10: Автоматическое ревью, объяснение ошибок, подсказки по исправлению | E10: 0.06 | F10: 0.3 | G10: 0.4 | H10: 0 | I10: 1 | J10: 0 | K10: 0 | L10: =E10*(1-F10) -> 0.042 | M10: =E10*(1-G10) -> 0.036
A11: Изменения | B11: DevOps | C11: Сборка, стенды, деплой | D11: Генерация пайплайнов и конфигураций, разбор падений сборки | E11: 0.04 | F11: 0.15 | G11: 0.2 | H11: 0 | I11: 0 | J11: 1 | K11: 0 | L11: =E11*(1-F11) -> 0.034 | M11: =E11*(1-G11) -> 0.032
A12: Изменения | B12: Тестирование | C12: Тест-дизайн и тест-кейсы | D12: Генерация тест-кейсов из постановки и критериев приёмки | E12: 0.08 | F12: 0.5 | G12: 0.6 | H12: 0 | I12: 0 | J12: 1 | K12: 0 | L12: =E12*(1-F12) -> 0.04 | M12: =E12*(1-G12) -> 0.032
A13: Изменения | B13: Тестирование | C13: Тестовые данные (сделки, позиции, остатки) | D13: Генерация наборов данных под сценарии | E13: 0.08 | F13: 0.4 | G13: 0.55 | H13: 0 | I13: 0 | J13: 1 | K13: 0 | L13: =E13*(1-F13) -> 0.048 | M13: =E13*(1-G13) -> 0.036
A14: Изменения | B14: Тестирование | C14: Прогон, регресс, автотесты | D14: Агент пишет и поддерживает автотесты | E14: 0.1 | F14: 0.5 | G14: 0.65 | H14: 0 | I14: 0 | J14: 1 | K14: 0 | L14: =E14*(1-F14) -> 0.05 | M14: =E14*(1-G14) -> 0.035
A15: Изменения | B15: Тестирование | C15: Анализ дефектов и ретесты | D15: Локализация причины, черновик исправления | E15: 0.06 | F15: 0.25 | G15: 0.35 | H15: 0 | I15: 0.5 | J15: 0.5 | K15: 0 | L15: =E15*(1-F15) -> 0.045 | M15: =E15*(1-G15) -> 0.039
A16: Изменения | B16: Тестирование | C16: ПСИ с заказчиком | D16: Программа и протоколы испытаний; сами испытания не ускоряет | E16: 0.08 | F16: 0.05 | G16: 0.1 | H16: 0.5 | I16: 0 | J16: 0.5 | K16: 0 | L16: =E16*(1-F16) -> 0.076 | M16: =E16*(1-G16) -> 0.072
A17: Сопровождение | B17: Сопровождение | C17: Приём и классификация обращений | D17: Автоклассификация, маршрутизация, поиск похожих обращений | E17: 0.15 | F17: 0.5 | G17: 0.6 | H17: 1 | I17: 0 | J17: 0 | K17: 0 | L17: =E17*(1-F17) -> 0.075 | M17: =E17*(1-G17) -> 0.06
A18: Сопровождение | B18: Сопровождение | C18: Диагностика: логи, данные, воспроизведение | D18: Анализ логов и данных, гипотезы причины | E18: 0.4 | F18: 0.3 | G18: 0.45 | H18: 0.5 | I18: 0.5 | J18: 0 | K18: 0 | L18: =E18*(1-F18) -> 0.28 | M18: =E18*(1-G18) -> 0.22
... A26: Пресейлы | B26: Пресейлы | C26: Подготовка материалов и оценок | D26: Черновики материалов, оценки по аналогам | E26: 0.5 | F26: 0.3 | G26: 0.45 | H26: 0.5 | I26: 0.5 | J26: 0 | K26: 0 | L26: =E26*(1-F26) -> 0.35 | M26: =E26*(1-G26) -> 0.275

Sheet Расчёт
A1: Расчёт экономии и потребности в людях
A3: Группа атомов | B3: Σw (проверка) | C3: E база | D3: E опт
A4: Изменения | B4: =SUMIF(Атомы!$A$5:$A$26,A4,Атомы!$E$5:$E$26) -> 1 | C4: =1-SUMIF(Атомы!$A$5:$A$26,A4,Атомы!$L$5:$L$26)/B4 -> 0.344 | D4: =1-SUMIF(Атомы!$A$5:$A$26,A4,Атомы!$M$5:$M$26)/B4 -> 0.435
A5: Сопровождение | B5: =SUMIF(Атомы!$A$5:$A$26,A5,Атомы!$E$5:$E$26) -> 1 | C5: =1-SUMIF(Атомы!$A$5:$A$26,A5,Атомы!$L$5:$L$26)/B5 -> 0.33 | D5: =1-SUMIF(Атомы!$A$5:$A$26,A5,Атомы!$M$5:$M$26)/B5 -> 0.4675
A6: Внедрение | B6: =SUMIF(Атомы!$A$5:$A$26,A6,Атомы!$E$5:$E$26) -> 1 | C6: =1-SUMIF(Атомы!$A$5:$A$26,A6,Атомы!$L$5:$L$26)/B6 -> 0.2 | D6: =1-SUMIF(Атомы!$A$5:$A$26,A6,Атомы!$M$5:$M$26)/B6 -> 0.3125
A7: Пресейлы | B7: =SUMIF(Атомы!$A$5:$A$26,A7,Атомы!$E$5:$E$26) -> 1 | C7: =1-SUMIF(Атомы!$A$5:$A$26,A7,Атомы!$L$5:$L$26)/B7 -> 0.15 | D7: =1-SUMIF(Атомы!$A$5:$A$26,A7,Атомы!$M$5:$M$26)/B7 -> 0.25
A9: Вид работ | B9: FTE AS-IS | C9: Группа | D9: E база | E9: E опт | F9: Нужно: консерв. | G9: Нужно: базовый | H9: Нужно: оптим.
A10: =Параметры!A14 -> Заказные доработки | B10: =Параметры!C14 -> 9.6 | C10: =Параметры!D14 -> Изменения | D10: =INDEX($C$4:$C$7,MATCH(C10,$A$4:$A$7,0)) -> 0.344 | E10: =INDEX($D$4:$D$7,MATCH(C10,$A$4:$A$7,0)) -> 0.435 | F10: =$B10*(1-Параметры!B$23*IF(Параметры!B$24="опт",$E10,$D10)) -> 6.95808 | G10: =$B10*(1-Параметры!C$23*IF(Параметры!C$24="опт",$E10,$D10)) -> 6.2976 | H10: =$B10*(1-Параметры!D$23*IF(Параметры!D$24="опт",$E10,$D10)) -> 5.424
A11: =Параметры!A15 -> Поддержка законодательства | B11: =Параметры!C15 -> 14.4 | C11: =Параметры!D15 -> Изменения | D11: =INDEX($C$4:$C$7,MATCH(C11,$A$4:$A$7,0)) -> 0.344 | E11: =INDEX($D$4:$D$7,MATCH(C11,$A$4:$A$7,0)) -> 0.435 | F11: =$B11*(1-Параметры!B$23*IF(Параметры!B$24="опт",$E11,$D11)) -> 10.43712 | G11: =$B11*(1-Параметры!C$23*IF(Параметры!C$24="опт",$E11,$D11)) -> 9.4464 | H11: =$B11*(1-Параметры!D$23*IF(Параметры!D$24="опт",$E11,$D11)) -> 8.136
A12: =Параметры!A16 -> Развитие продукта | B12: =Параметры!C16 -> 4.8 | C12: =Параметры!D16 -> Изменения | D12: =INDEX($C$4:$C$7,MATCH(C12,$A$4:$A$7,0)) -> 0.344 | E12: =INDEX($D$4:$D$7,MATCH(C12,$A$4:$A$7,0)) -> 0.435 | F12: =$B12*(1-Параметры!B$23*IF(Параметры!B$24="опт",$E12,$D12)) -> 3.47904 | G12: =$B12*(1-Параметры!C$23*IF(Параметры!C$24="опт",$E12,$D12)) -> 3.1488 | H12: =$B12*(1-Параметры!D$23*IF(Параметры!D$24="опт",$E12,$D12)) -> 2.712
A13: =Параметры!A17 -> Поддержка проектов внедрения | B13: =Параметры!C17 -> 4.8 | C13: =Параметры!D17 -> Внедрение | D13: =INDEX($C$4:$C$7,MATCH(C13,$A$4:$A$7,0)) -> 0.2 | E13: =INDEX($D$4:$D$7,MATCH(C13,$A$4:$A$7,0)) -> 0.3125 | F13: =$B13*(1-Параметры!B$23*IF(Параметры!B$24="опт",$E13,$D13)) -> 4.032 | G13: =$B13*(1-Параметры!C$23*IF(Параметры!C$24="опт",$E13,$D13)) -> 3.84 | H13: =$B13*(1-Параметры!D$23*IF(Параметры!D$24="опт",$E13,$D13)) -> 3.3
A14: =Параметры!A18 -> Сопровождение | B14: =Параметры!C18 -> 12 | C14: =Параметры!D18 -> Сопровождение | D14: =INDEX($C$4:$C$7,MATCH(C14,$A$4:$A$7,0)) -> 0.33 | E14: =INDEX($D$4:$D$7,MATCH(C14,$A$4:$A$7,0)) -> 0.4675 | F14: =$B14*(1-Параметры!B$23*IF(Параметры!B$24="опт",$E14,$D14)) -> 8.832 | G14: =$B14*(1-Параметры!C$23*IF(Параметры!C$24="опт",$E14,$D14)) -> 8.04 | H14: =$B14*(1-Параметры!D$23*IF(Параметры!D$24="опт",$E14,$D14)) -> 6.39
A15: =Параметры!A19 -> Пресейлы и обследования | B15: =Параметры!C19 -> 2.4 | C15: =Параметры!D19 -> Пресейлы | D15: =INDEX($C$4:$C$7,MATCH(C15,$A$4:$A$7,0)) -> 0.15 | E15: =INDEX($D$4:$D$7,MATCH(C15,$A$4:$A$7,0)) -> 0.25 | F15: =$B15*(1-Параметры!B$23*IF(Параметры!B$24="опт",$E15,$D15)) -> 2.112 | G15: =$B15*(1-Параметры!C$23*IF(Параметры!C$24="опт",$E15,$D15)) -> 2.04 | H15: =$B15*(1-Параметры!D$23*IF(Параметры!D$24="опт",$E15,$D15)) -> 1.8
A16: Итого до накладных | B16: =SUM(B10:B15) -> 48 | F16: =SUM(F10:F15) -> 35.85024 | G16: =SUM(G10:G15) -> 32.8128 | H16: =SUM(H10:H15) -> 27.762
A17: + накладные ИИ (o) | F17: =F16*Параметры!B25 -> 1.792512 | G17: =G16*Параметры!C25 -> 1.64064 | H17: =H16*Параметры!D25 -> 1.3881
A18: − снижение переделок (R) | F18: =SUMIF($C$10:$C$15,"Изменения",F10:F15)*Параметры!B26*Параметры!B27 -> 1.043712 | G18: =SUMIF($C$10:$C$15,"Изменения",G10:G15)*Параметры!C26*Параметры!C27 -> 0.94464 | H18: =SUMIF($C$10:$C$15,"Изменения",H10:H15)*Параметры!D26*Параметры!D27 -> 0.8136
A19: Нужно исполнителей | F19: =F16+F17-F18 -> 36.59904 | G19: =G16+G17-G18 -> 33.5088 | H19: =H16+H17-H18 -> 28.3365
A20: Экономия на исполнителях к AS-IS | F20: =1-F19/$B$16 -> 0.23752 | G20: =1-G19/$B$16 -> 0.3019 | H20: =1-H19/$B$16 -> 0.40965625
A22: Группа (доли часов по ролям) | B22: А as-is | C22: Р as-is | D22: Т as-is | E22: А база | F22: Р база | G22: Т база | H22: А опт | I22: Р опт | J22: Т опт | K22: Intent as-is | L22: Intent база | M22: Intent опт
A24: Изменения | B24: =SUMPRODUCT((Атомы!$A$5:$A$26=$A24)*Атомы!$E$5:$E$26*Атомы!$H$5:$H$26)/INDEX($B$4:$B$7,MATCH($A24,$A$4:$A$7,0)) -> 0.34 | C24: =SUMPRODUCT((Атомы!$A$5:$A$26=$A24)*Атомы!$E$5:$E$26*Атомы!$I$5:$I$26)/INDEX($B$4:$B$7,MATCH($A24,$A$4:$A$7,0)) -> 0.29 | D24: =SUMPRODUCT((Атомы!$A$5:$A$26=$A24)*Атомы!$E$5:$E$26*Атомы!$J$5:$J$26)/INDEX($B$4:$B$7,MATCH($A24,$A$4:$A$7,0)) -> 0.37 | E24: =SUMPRODUCT((Атомы!$A$5:$A$26=$A24)*Атомы!$L$5:$L$26*Атомы!$H$5:$H$26)/INDEX($B$4:$B$7,MATCH($A24,$A$4:$A$7,0)) -> 0.244 | F24: =SUMPRODUCT((Атомы!$A$5:$A$26=$A24)*Атомы!$L$5:$L$26*Атомы!$I$5:$I$26)/INDEX($B$4:$B$7,MATCH($A24,$A$4:$A$7,0)) -> 0.1795 | G24: =SUMPRODUCT((Атомы!$A$5:$A$26=$A24)*Атомы!$L$5:$L$26*Атомы!$J$5:$J$26)/INDEX($B$4:$B$7,MATCH($A24,$A$4:$A$7,0)) -> 0.2325 | H24: =SUMPRODUCT((Атомы!$A$5:$A$26=$A24)*Атомы!$M$5:$M$26*Атомы!$H$5:$H$26)/INDEX($B$4:$B$7,MATCH($A24,$A$4:$A$7,0)) -> 0.224 | I24: =SUMPRODUCT((Атомы!$A$5:$A$26=$A24)*Атомы!$M$5:$M$26*Атомы!$I$5:$I$26)/INDEX($B$4:$B$7,MATCH($A24,$A$4:$A$7,0)) -> 0.1505 | J24: =SUMPRODUCT((Атомы!$A$5:$A$26=$A24)*Атомы!$M$5:$M$26*Атомы!$J$5:$J$26)/INDEX($B$4:$B$7,MATCH($A24,$A$4:$A$7,0)) -> 0.1905 | K24: =SUMPRODUCT((Атомы!$A$5:$A$26=$A24)*Атомы!$E$5:$E$26*Атомы!$K$5:$K$26)/INDEX($B$4:$B$7,MATCH($A24,$A$4:$A$7,0)) -> 0.14 | L24: =SUMPRODUCT((Атомы!$A$5:$A$26=$A24)*Атомы!$L$5:$L$26*Атомы!$K$5:$K$26)/INDEX($B$4:$B$7,MATCH($A24,$A$4:$A$7,0)) -> 0.1092 | M24: =SUMPRODUCT((Атомы!$A$5:$A$26=$A24)*Атомы!$M$5:$M$26*Атомы!$K$5:$K$26)/INDEX($B$4:$B$7,MATCH($A24,$A$4:$A$7,0)) -> 0.1036
A25: Сопровождение | B25: =SUMPRODUCT((Атомы!$A$5:$A$26=$A25)*Атомы!$E$5:$E$26*Атомы!$H$5:$H$26)/INDEX($B$4:$B$7,MATCH($A25,$A$4:$A$7,0)) -> 0.5 | C25: =SUMPRODUCT((Атомы!$A$5:$A$26=$A25)*Атомы!$E$5:$E$26*Атомы!$I$5:$I$26)/INDEX($B$4:$B$7,MATCH($A25,$A$4:$A$7,0)) -> 0.4 | D25: =SUMPRODUCT((Атомы!$A$5:$A$26=$A25)*Атомы!$E$5:$E$26*Атомы!$J$5:$J$26)/INDEX($B$4:$B$7,MATCH($A25,$A$4:$A$7,0)) -> 0.1 | E25: =SUMPRODUCT((Атомы!$A$5:$A$26=$A25)*Атомы!$L$5:$L$26*Атомы!$H$5:$H$26)/INDEX($B$4:$B$7,MATCH($A25,$A$4:$A$7,0)) -> 0.32 | F25: =SUMPRODUCT((Атомы!$A$5:$A$26=$A25)*Атомы!$L$5:$L$26*Атомы!$I$5:$I$26)/INDEX($B$4:$B$7,MATCH($A25,$A$4:$A$7,0)) -> 0.27 | G25: =SUMPRODUCT((Атомы!$A$5:$A$26=$A25)*Атомы!$L$5:$L$26*Атомы!$J$5:$J$26)/INDEX($B$4:$B$7,MATCH($A25,$A$4:$A$7,0)) -> 0.08 | H25: =SUMPRODUCT((Атомы!$A$5:$A$26=$A25)*Атомы!$M$5:$M$26*Атомы!$H$5:$H$26)/INDEX($B$4:$B$7,MATCH($A25,$A$4:$A$7,0)) -> 0.2525 | I25: =SUMPRODUCT((Атомы!$A$5:$A$26=$A25)*Атомы!$M$5:$M$26*Атомы!$I$5:$I$26)/INDEX($B$4:$B$7,MATCH($A25,$A$4:$A$7,0)) -> 0.21 | J25: =SUMPRODUCT((Атомы!$A$5:$A$26=$A25)*Атомы!$M$5:$M$26*Атомы!$J$5:$J$26)/INDEX($B$4:$B$7,MATCH($A25,$A$4:$A$7,0)) -> 0.07 | K25: =SUMPRODUCT((Атомы!$A$5:$A$26=$A25)*Атомы!$E$5:$E$26*Атомы!$K$5:$K$26)/INDEX($B$4:$B$7,MATCH($A25,$A$4:$A$7,0)) -> 0 | L25: =SUMPRODUCT((Атомы!$A$5:$A$26=$A25)*Атомы!$L$5:$L$26*Атомы!$K$5:$K$26)/INDEX($B$4:$B$7,MATCH($A25,$A$4:$A$7,0)) -> 0 | M25: =SUMPRODUCT((Атомы!$A$5:$A$26=$A25)*Атомы!$M$5:$M$26*Атомы!$K$5:$K$26)/INDEX($B$4:$B$7,MATCH($A25,$A$4:$A$7,0)) -> 0
A26: Внедрение | B26: =SUMPRODUCT((Атомы!$A$5:$A$26=$A26)*Атомы!$E$5:$E$26*Атомы!$H$5:$H$26)/INDEX($B$4:$B$7,MATCH($A26,$A$4:$A$7,0)) -> 0.625 | C26: =SUMPRODUCT((Атомы!$A$5:$A$26=$A26)*Атомы!$E$5:$E$26*Атомы!$I$5:$I$26)/INDEX($B$4:$B$7,MATCH($A26,$A$4:$A$7,0)) -> 0.125 | D26: =SUMPRODUCT((Атомы!$A$5:$A$26=$A26)*Атомы!$E$5:$E$26*Атомы!$J$5:$J$26)/INDEX($B$4:$B$7,MATCH($A26,$A$4:$A$7,0)) -> 0.25 | E26: =SUMPRODUCT((Атомы!$A$5:$A$26=$A26)*Атомы!$L$5:$L$26*Атомы!$H$5:$H$26)/INDEX($B$4:$B$7,MATCH($A26,$A$4:$A$7,0)) -> 0.5 | F26: =SUMPRODUCT((Атомы!$A$5:$A$26=$A26)*Атомы!$L$5:$L$26*Атомы!$I$5:$I$26)/INDEX($B$4:$B$7,MATCH($A26,$A$4:$A$7,0)) -> 0.1 | G26: =SUMPRODUCT((Атомы!$A$5:$A$26=$A26)*Атомы!$L$5:$L$26*Атомы!$J$5:$J$26)/INDEX($B$4:$B$7,MATCH($A26,$A$4:$A$7,0)) -> 0.2 | H26: =SUMPRODUCT((Атомы!$A$5:$A$26=$A26)*Атомы!$M$5:$M$26*Атомы!$H$5:$H$26)/INDEX($B$4:$B$7,MATCH($A26,$A$4:$A$7,0)) -> 0.4375 | I26: =SUMPRODUCT((Атомы!$A$5:$A$26=$A26)*Атомы!$M$5:$M$26*Атомы!$I$5:$I$26)/INDEX($B$4:$B$7,MATCH($A26,$A$4:$A$7,0)) -> 0.08125 | J26: =SUMPRODUCT((Атомы!$A$5:$A$26=$A26)*Атомы!$M$5:$M$26*Атомы!$J$5:$J$26)/INDEX($B$4:$B$7,MATCH($A26,$A$4:$A$7,0)) -> 0.16875 | K26: =SUMPRODUCT((Атомы!$A$5:$A$26=$A26)*Атомы!$E$5:$E$26*Атомы!$K$5:$K$26)/INDEX($B$4:$B$7,MATCH($A26,$A$4:$A$7,0)) -> 0.5 | L26: =SUMPRODUCT((Атомы!$A$5:$A$26=$A26)*Атомы!$L$5:$L$26*Атомы!$K$5:$K$26)/INDEX($B$4:$B$7,MATCH($A26,$A$4:$A$7,0)) -> 0.4 | M26: =SUMPRODUCT((Атомы!$A$5:$A$26=$A26)*Атомы!$M$5:$M$26*Атомы!$K$5:$K$26)/INDEX($B$4:$B$7,MATCH($A26,$A$4:$A$7,0)) -> 0.35
A27: Пресейлы | B27: =SUMPRODUCT((Атомы!$A$5:$A$26=$A27)*Атомы!$E$5:$E$26*Атомы!$H$5:$H$26)/INDEX($B$4:$B$7,MATCH($A27,$A$4:$A$7,0)) -> 0.75 | C27: =SUMPRODUCT((Атомы!$A$5:$A$26=$A27)*Атомы!$E$5:$E$26*Атомы!$I$5:$I$26)/INDEX($B$4:$B$7,MATCH($A27,$A$4:$A$7,0)) -> 0.25 | D27: =SUMPRODUCT((Атомы!$A$5:$A$26=$A27)*Атомы!$E$5:$E$26*Атомы!$J$5:$J$26)/INDEX($B$4:$B$7,MATCH($A27,$A$4:$A$7,0)) -> 0 | E27: =SUMPRODUCT((Атомы!$A$5:$A$26=$A27)*Атомы!$L$5:$L$26*Атомы!$H$5:$H$26)/INDEX($B$4:$B$7,MATCH($A27,$A$4:$A$7,0)) -> 0.675 | F27: =SUMPRODUCT((Атомы!$A$5:$A$26=$A27)*Атомы!$L$5:$L$26*Атомы!$I$5:$I$26)/INDEX($B$4:$B$7,MATCH($A27,$A$4:$A$7,0)) -> 0.175 | G27: =SUMPRODUCT((Атомы!$A$5:$A$26=$A27)*Атомы!$L$5:$L$26*Атомы!$J$5:$J$26)/INDEX($B$4:$B$7,MATCH($A27,$A$4:$A$7,0)) -> 0 | H27: =SUMPRODUCT((Атомы!$A$5:$A$26=$A27)*Атомы!$M$5:$M$26*Атомы!$H$5:$H$26)/INDEX($B$4:$B$7,MATCH($A27,$A$4:$A$7,0)) -> 0.6125 | I27: =SUMPRODUCT((Атомы!$A$5:$A$26=$A27)*Атомы!$M$5:$M$26*Атомы!$I$5:$I$26)/INDEX($B$4:$B$7,MATCH($A27,$A$4:$A$7,0)) -> 0.1375 | J27: =SUMPRODUCT((Атомы!$A$5:$A$26=$A27)*Атомы!$M$5:$M$26*Атомы!$J$5:$J$26)/INDEX($B$4:$B$7,MATCH($A27,$A$4:$A$7,0)) -> 0 | K27: =SUMPRODUCT((Атомы!$A$5:$A$26=$A27)*Атомы!$E$5:$E$26*Атомы!$K$5:$K$26)/INDEX($B$4:$B$7,MATCH($A27,$A$4:$A$7,0)) -> 0 | L27: =SUMPRODUCT((Атомы!$A$5:$A$26=$A27)*Атомы!$L$5:$L$26*Атомы!$K$5:$K$26)/INDEX($B$4:$B$7,MATCH($A27,$A$4:$A$7,0)) -> 0 | M27: =SUMPRODUCT((Атомы!$A$5:$A$26=$A27)*Атомы!$M$5:$M$26*Атомы!$K$5:$K$26)/INDEX($B$4:$B$7,MATCH($A27,$A$4:$A$7,0)) -> 0
A29: FTE по группам | B29: FTE AS-IS
A30: Изменения | B30: =SUMIF($C$10:$C$15,A30,$B$10:$B$15) -> 28.8
A31: Сопровождение | B31: =SUMIF($C$10:$C$15,A31,$B$10:$B$15) -> 12
A32: Внедрение | B32: =SUMIF($C$10:$C$15,A32,$B$10:$B$15) -> 4.8
A33: Пресейлы | B33: =SUMIF($C$10:$C$15,A33,$B$10:$B$15) -> 2.4
A35: Потребность по ролям | B35: Работа AS-IS | C35: Консерв. | D35: Базовый | E35: Оптим. | F35: Штат AS-IS
A36: Аналитика (включая Intent-команду) | B36: =SUMPRODUCT($B$30:$B$33,B24:B27) -> 20.592 | C36: =SUMPRODUCT($B$30:$B$33,(1-Параметры!B$23)*B24:B27+Параметры!B$23*((Параметры!B$24="опт")*H24:H27+(1-(Параметры!B$24="опт"))*E24:E27))+F$17*0-F$18*Параметры!$B$34 -> 15.715046 | D36: =SUMPRODUCT($B$30:$B$33,(1-Параметры!C$23)*B24:B27+Параметры!C$23*((Параметры!C$24="опт")*H24:H27+(1-(Параметры!C$24="опт"))*E24:E27))+G$17*0-G$18*Параметры!$B$34 -> 14.603808 | E36: =SUMPRODUCT($B$30:$B$33,(1-Параметры!D$23)*B24:B27+Параметры!D$23*((Параметры!D$24="опт")*H24:H27+(1-(Параметры!D$24="опт"))*E24:E27))+H$17*0-H$18*Параметры!$B$34 -> 12.80712 | F36: =Параметры!$B$4*Параметры!B6 -> 12
A37: Разработка | B37: =SUMPRODUCT($B$30:$B$33,C24:C27) -> 14.352 | C37: =SUMPRODUCT($B$30:$B$33,(1-Параметры!B$23)*C24:C27+Параметры!B$23*((Параметры!B$24="опт")*I24:I27+(1-(Параметры!B$24="опт"))*F24:F27))+F$17*Параметры!$B$32-F$18*Параметры!$B$35 -> 10.901222 | D37: =SUMPRODUCT($B$30:$B$33,(1-Параметры!C$23)*C24:C27+Параметры!C$23*((Параметры!C$24="опт")*I24:I27+(1-(Параметры!C$24="опт"))*F24:F27))+G$17*Параметры!$B$32-G$18*Параметры!$B$35 -> 9.846528 | E37: =SUMPRODUCT($B$30:$B$33,(1-Параметры!D$23)*C24:C27+Параметры!D$23*((Параметры!D$24="опт")*I24:I27+(1-(Параметры!D$24="опт"))*F24:F27))+H$17*Параметры!$B$32-H$18*Параметры!$B$35 -> 8.02437 | F37: =Параметры!$B$4*Параметры!B7 -> 24
A38: Тестирование и DevOps | B38: =SUMPRODUCT($B$30:$B$33,D24:D27) -> 13.056 | C38: =SUMPRODUCT($B$30:$B$33,(1-Параметры!B$23)*D24:D27+Параметры!B$23*((Параметры!B$24="опт")*J24:J27+(1-(Параметры!B$24="опт"))*G24:G27))+F$17*Параметры!$B$33-F$18*Параметры!$B$36 -> 9.9827712 | D38: =SUMPRODUCT($B$30:$B$33,(1-Параметры!C$23)*D24:D27+Параметры!C$23*((Параметры!C$24="опт")*J24:J27+(1-(Параметры!C$24="опт"))*G24:G27))+G$17*Параметры!$B$33-G$18*Параметры!$B$36 -> 9.058464 | E38: =SUMPRODUCT($B$30:$B$33,(1-Параметры!D$23)*D24:D27+Параметры!D$23*((Параметры!D$24="опт")*J24:J27+(1-(Параметры!D$24="опт"))*G24:G27))+H$17*Параметры!$B$33-H$18*Параметры!$B$36 -> 7.50501 | F38: =Параметры!$B$4*Параметры!B8 -> 12
A39: Итого исполнителей | B39: =SUM(B36:B38) -> 48 | C39: =SUM(C36:C38) -> 36.59904 | D39: =SUM(D36:D38) -> 33.5088 | E39: =SUM(E36:E38) -> 28.3365 | F39: =SUM(F36:F38) -> 48
A40: из них работа Intent-команды | B40: =SUMPRODUCT($B$30:$B$33,$K$24:$K$27) -> 6.432 | C40: =SUMPRODUCT($B$30:$B$33,(1-Параметры!B$23)*$K$24:$K$27+Параметры!B$23*((Параметры!B$24="опт")*$M$24:$M$27+(1-(Параметры!B$24="опт"))*$L$24:$L$27)) -> 5.338368 | D40: =SUMPRODUCT($B$30:$B$33,(1-Параметры!C$23)*$K$24:$K$27+Параметры!C$23*((Параметры!C$24="опт")*$M$24:$M$27+(1-(Параметры!C$24="опт"))*$L$24:$L$27)) -> 5.06496 | E40: =SUMPRODUCT($B$30:$B$33,(1-Параметры!D$23)*$K$24:$K$27+Параметры!D$23*((Параметры!D$24="опт")*$M$24:$M$27+(1-(Параметры!D$24="опт"))*$L$24:$L$27)) -> 4.66368
A42: «Работа AS-IS» — сколько человек нужно под аналитику, разработку и тестирование по раскладке атомов; «Штат AS-IS» — сколько людей в этих ролях сейчас. Разница показывает, какую часть аналитики и диагностики сегодня фактически делают разработчики.

Sheet Структура
A1: Целевая структура и сверка с потребностью
A3: Команда | B3: Кол-во | C3: РК | D3: Аналитики | E3: Разработчики | F3: Тестировщики-DevOps | G3: В команде | H3: Всего
A4: Intent-команда (discovery и intent) | B4: 1 | C4: 0 | D4: 5 | E4: 0 | F4: 0 | G4: =SUM(C4:F4) -> 5 | H4: =B4*G4 -> 5
A5: Продуктовый учёт по всем рынкам | B5: 1 | C5: 1 | D5: 2 | E5: 2 | F5: 1 | G5: =SUM(C5:F5) -> 6 | H5: =B5*G5 -> 6
A6: Внутренний, бухгалтерский и доверительный учёт | B6: 1 | C6: 1 | D6: 2 | E6: 2 | F6: 1 | G6: =SUM(C6:F6) -> 6 | H6: =B6*G6 -> 6
A7: НДФЛ | B7: 1 | C7: 1 | D7: 2 | E7: 2 | F7: 1 | G7: =SUM(C7:F7) -> 6 | H7: =B7*G7 -> 6
A8: Кор-команда по финансовым инструментам (платформы FA и MSA) | B8: 1 | C8: 1 | D8: 1 | E8: 3 | F8: 2 | G8: =SUM(C8:F8) -> 7 | H8: =B8*G8 -> 7
A9: Микросервисная команда (рыночные данные и прочие сервисы) | B9: 1 | C9: 1 | D9: 1 | E9: 2 | F9: 2 | G9: =SUM(C9:F9) -> 6 | H9: =B9*G9 -> 6
A10: Роли вне команд | H10: =Параметры!B9 -> 6
A11: Итого TO-BE | C11: =SUMPRODUCT($B$4:$B$9,C4:C9) -> 5 | D11: =SUMPRODUCT($B$4:$B$9,D4:D9) -> 13 | E11: =SUMPRODUCT($B$4:$B$9,E4:E9) -> 11 | F11: =SUMPRODUCT($B$4:$B$9,F4:F9) -> 7 | H11: =SUM(H4:H9)+H10 -> 42
A12: Итого AS-IS | H12: =Параметры!B11 -> 60
A13: Изменение численности | H13: =H11/H12-1 -> -0.3
A15: Сверка предложения с потребностью | B15: Есть | C15: Консерв. | D15: Базовый | E15: Оптим. | F15: Разрыв к базовому
A16: Аналитика (включая Intent-команду) | B16: =D11 -> 13 | C16: =Расчёт!C36 -> 15.715046 | D16: =Расчёт!D36 -> 14.603808 | E16: =Расчёт!E36 -> 12.80712 | F16: =B16-D16 -> -1.603808
A17: Разработка | B17: =E11 -> 11 | C17: =Расчёт!C37 -> 10.901222 | D17: =Расчёт!D37 -> 9.846528 | E17: =Расчёт!E37 -> 8.02437 | F17: =B17-D17 -> 1.153472
A18: Тестирование и DevOps | B18: =F11 -> 7 | C18: =Расчёт!C38 -> 9.9827712 | D18: =Расчёт!D38 -> 9.058464 | E18: =Расчёт!E38 -> 7.50501 | F18: =B18-D18 -> -2.058464
A19: Руководители на задачах (РК × доля времени) | B19: =C11*Параметры!B31 -> 2.5 | F19: =B19-D19 -> 2.5
A20: Итого исполнителей | B20: =SUM(B16:B19) -> 33.5 | C20: =SUM(C16:C19) -> 36.59904 | D20: =SUM(D16:D19) -> 33.5088 | E20: =SUM(E16:E19) -> 28.3365 | F20: =SUM(F16:F19) -> -0.0088
A21: Intent-команда: есть / нужно по базовому | B21: =D4*B4 -> 5 | D21: =Расчёт!D40 -> 5.06496 | F21: =B21-D21 -> -0.06496
A23: Отрицательный разрыв в тестировании закрывают продуктовые инженеры: избыток разработки и руководители уходят в автотесты с агентами.
